tiny_flags/__init__.py
tiny_flags/bitfield.py
tiny_flags/tiny_flags.py
tiny_flags/validations.py
tiny_flags-1.0.0.dist-info/LICENCE
tiny_flags-1.0.0.dist-info/METADATA
tiny_flags-1.0.0.dist-info/WHEEL
tiny_flags-1.0.0.dist-info/top_level.txt
tiny_flags-1.0.0.dist-info/RECORD
