Metadata-Version: 2.1
Name: tiny_flags
Version: 1.0.0
Summary: Map options/flags to methods using 32 or 64bit integers for optimized state management.
Author-email: Kaarle Kulvik <k.kulvik@gmail.com>
Project-URL: Homepage, https://github.com/FistOfTheNorthStar/tiny_flags
Project-URL: Issues, https://github.com/FistOfTheNorthStar/tiny_flags/issues
Classifier: Programming Language :: Python :: 3
Classifier: License :: OSI Approved :: MIT License
Classifier: Operating System :: OS Independent
Requires-Python: >=3.8
License-File: LICENCE
Provides-Extra: dev
Requires-Dist: pytest>=8.3.4; extra == "dev"
Requires-Dist: flake8>=7.1.1; extra == "dev"
Requires-Dist: black>=24.10.0; extra == "dev"
Requires-Dist: isort>=5.13.2; extra == "dev"
